dvpOAuth/__init__.py
dvpOAuth/class_OAuth.py
dvpOAuth/error.py
dvpOAuth/util.py
dvpOAuth-0.0.21.dist-info/LICENSE
dvpOAuth-0.0.21.dist-info/METADATA
dvpOAuth-0.0.21.dist-info/WHEEL
dvpOAuth-0.0.21.dist-info/top_level.txt
dvpOAuth-0.0.21.dist-info/RECORD
